{
    "sessions": {
        "NY": {
            "name": "NY",
            "timeRange": "7:00 AM - 5:00 PM CT",
            "breaches": [
                {
                    "pair": "USDCAD",
                    "type": "HIGH",
                    "pips": 2.4008750915527344,
                    "previousSession": "LONDON",
                    "timestamp": "2025-09-19T07:18:00-05:00",
                    "time": "07:18:00"
                },
                {
                    "pair": "EURCAD",
                    "type": "LOW",
                    "pips": 3.4999847412109375,
                    "previousSession": "LONDON",
                    "timestamp": "2025-09-19T07:01:00-05:00",
                    "time": "07:01:00"
                },
                {
                    "pair": "GBPCAD",
                    "type": "LOW",
                    "pips": 4.800558090209961,
                    "previousSession": "LONDON",
                    "timestamp": "2025-09-19T07:01:00-05:00",
                    "time": "07:01:00"
                },
                {
                    "pair": "CADCHF",
                    "type": "HIGH",
                    "pips": 0.29981136322021484,
                    "previousSession": "LONDON",
                    "timestamp": "2025-09-19T07:08:00-05:00",
                    "time": "07:08:00"
                },
                {
                    "pair": "AUDCAD",
                    "type": "LOW",
                    "pips": 2.499818801879883,
                    "previousSession": "LONDON",
                    "timestamp": "2025-09-19T07:02:00-05:00",
                    "time": "07:02:00"
                },
                {
                    "pair": "NZDCAD",
                    "type": "LOW",
                    "pips": 1.099705696105957,
                    "previousSession": "LONDON",
                    "timestamp": "2025-09-19T07:01:00-05:00",
                    "time": "07:01:00"
                },
                {
                    "pair": "EURUSD",
                    "type": "LOW",
                    "pips": 4.131793975830078,
                    "previousSession": "LONDON",
                    "timestamp": "2025-09-19T07:22:00-05:00",
                    "time": "07:22:00"
                },
                {
                    "pair": "GBPUSD",
                    "type": "LOW",
                    "pips": 4.355907440185547,
                    "previousSession": "LONDON",
                    "timestamp": "2025-09-19T07:01:00-05:00",
                    "time": "07:01:00"
                },
                {
                    "pair": "USDCHF",
                    "type": "HIGH",
                    "pips": 3.699660301208496,
                    "previousSession": "LONDON",
                    "timestamp": "2025-09-19T07:08:00-05:00",
                    "time": "07:08:00"
                },
                {
                    "pair": "NZDUSD",
                    "type": "LOW",
                    "pips": 3.0928850173950195,
                    "previousSession": "LONDON",
                    "timestamp": "2025-09-19T07:01:00-05:00",
                    "time": "07:01:00"
                },
                {
                    "pair": "EURCHF",
                    "type": "LOW",
                    "pips": 1.100301742553711,
                    "previousSession": "LONDON",
                    "timestamp": "2025-09-19T07:27:00-05:00",
                    "time": "07:27:00"
                },
                {
                    "pair": "AUDUSD",
                    "type": "LOW",
                    "pips": 3.9124488830566406,
                    "previousSession": "LONDON",
                    "timestamp": "2025-09-19T07:01:00-05:00",
                    "time": "07:01:00"
                },
                {
                    "pair": "EURJPY",
                    "type": "LOW",
                    "pips": 850.067138671875,
                    "previousSession": "LONDON",
                    "timestamp": "2025-09-19T07:01:00-05:00",
                    "time": "07:01:00"
                }
            ]
        }
    },
    "currentSession": "NY",
    "correlations": {
        "USD": 0.41399508044255234,
        "EUR": 0.22434377018474447,
        "GBP": 0.4289768683694547,
        "CAD": 0.1978546330681961,
        "CHF": 0.25614644888833726,
        "AUD": 0.35167805967287474,
        "NZD": 0.3433382645440711,
        "JPY": 0.7751084466790263
    }
}