{
    "sessions": {
        "LONDON": {
            "name": "LONDON",
            "timeRange": "2:00 AM - 7:00 AM CT",
            "breaches": [
                {
                    "pair": "GBPCAD",
                    "type": "HIGH",
                    "pips": 20.099878311157227,
                    "previousSession": "ASIA",
                    "timestamp": "2025-11-05T02:07:00-06:00",
                    "time": "02:07:00"
                },
                {
                    "pair": "GBPUSD",
                    "type": "HIGH",
                    "pips": 16.663074493408203,
                    "previousSession": "ASIA",
                    "timestamp": "2025-11-05T02:05:00-06:00",
                    "time": "02:05:00"
                },
                {
                    "pair": "EURCHF",
                    "type": "HIGH",
                    "pips": 0.9995698928833008,
                    "previousSession": "ASIA",
                    "timestamp": "2025-11-05T02:33:00-06:00",
                    "time": "02:33:00"
                },
                {
                    "pair": "EURGBP",
                    "type": "LOW",
                    "pips": 6.300210952758789,
                    "previousSession": "ASIA",
                    "timestamp": "2025-11-05T02:08:00-06:00",
                    "time": "02:08:00"
                },
                {
                    "pair": "GBPCHF",
                    "type": "HIGH",
                    "pips": 13.99993896484375,
                    "previousSession": "ASIA",
                    "timestamp": "2025-11-05T02:05:00-06:00",
                    "time": "02:05:00"
                },
                {
                    "pair": "EURJPY",
                    "type": "HIGH",
                    "pips": 50.048828125,
                    "previousSession": "ASIA",
                    "timestamp": "2025-11-05T02:15:00-06:00",
                    "time": "02:15:00"
                },
                {
                    "pair": "GBPJPY",
                    "type": "HIGH",
                    "pips": 1560.05859375,
                    "previousSession": "ASIA",
                    "timestamp": "2025-11-05T02:09:00-06:00",
                    "time": "02:09:00"
                }
            ]
        }
    },
    "currentSession": "LONDON",
    "correlations": {
        "USD": 0.2784376165070044,
        "EUR": 0.14038093655914644,
        "GBP": 0.2439900682018658,
        "CAD": 0.06412998570027889,
        "CHF": 0.18170257758648745,
        "AUD": 0.4718130358196378,
        "NZD": 0.3599241330988097,
        "JPY": 0.8051907511453538
    }
}