{
    "sessions": {
        "ASIA": {
            "name": "ASIA",
            "timeRange": "7:00 PM - 2:00 AM CT",
            "breaches": [
                {
                    "pair": "EURUSD",
                    "type": "HIGH",
                    "pips": 53.119659423828125,
                    "previousSession": "NY",
                    "timestamp": "2026-01-19T19:01:00-06:00",
                    "time": "19:01:00"
                },
                {
                    "pair": "GBPUSD",
                    "type": "HIGH",
                    "pips": 62.60871887207031,
                    "previousSession": "NY",
                    "timestamp": "2026-01-19T19:00:00-06:00",
                    "time": "19:00:00"
                },
                {
                    "pair": "NZDUSD",
                    "type": "HIGH",
                    "pips": 41.335225105285645,
                    "previousSession": "NY",
                    "timestamp": "2026-01-19T19:02:00-06:00",
                    "time": "19:02:00"
                },
                {
                    "pair": "AUDUSD",
                    "type": "HIGH",
                    "pips": 31.70490264892578,
                    "previousSession": "NY",
                    "timestamp": "2026-01-19T20:02:00-06:00",
                    "time": "20:02:00"
                }
            ]
        }
    },
    "currentSession": "LONDON",
    "correlations": {
        "USD": 0.2631928699992649,
        "EUR": 0.13030610584305483,
        "GBP": 0.26929967186979303,
        "CAD": 0.19445006494391606,
        "CHF": 0.3933036620640474,
        "AUD": 0.3970241430231943,
        "NZD": 0.5092696126666992,
        "JPY": 0.71409908447638
    }
}