{
    "sessions": {
        "NY": {
            "name": "NY",
            "timeRange": "7:00 AM - 5:00 PM CT",
            "breaches": [
                {
                    "pair": "USDCAD",
                    "type": "HIGH",
                    "pips": 1.2993812561035156,
                    "previousSession": "LONDON",
                    "timestamp": "2025-11-05T08:27:00-06:00",
                    "time": "08:27:00"
                },
                {
                    "pair": "EURCAD",
                    "type": "LOW",
                    "pips": 14.499425888061523,
                    "previousSession": "LONDON",
                    "timestamp": "2025-11-05T09:00:00-06:00",
                    "time": "09:00:00"
                },
                {
                    "pair": "GBPCAD",
                    "type": "LOW",
                    "pips": 4.199743270874023,
                    "previousSession": "LONDON",
                    "timestamp": "2025-11-05T09:00:00-06:00",
                    "time": "09:00:00"
                },
                {
                    "pair": "CADCHF",
                    "type": "HIGH",
                    "pips": 6.299614906311035,
                    "previousSession": "LONDON",
                    "timestamp": "2025-11-05T09:00:00-06:00",
                    "time": "09:00:00"
                },
                {
                    "pair": "AUDCAD",
                    "type": "HIGH",
                    "pips": 13.800263404846191,
                    "previousSession": "LONDON",
                    "timestamp": "2025-11-05T07:40:00-06:00",
                    "time": "07:40:00"
                },
                {
                    "pair": "NZDCAD",
                    "type": "HIGH",
                    "pips": 1.5997886657714844,
                    "previousSession": "LONDON",
                    "timestamp": "2025-11-05T09:28:00-06:00",
                    "time": "09:28:00"
                },
                {
                    "pair": "EURUSD",
                    "type": "LOW",
                    "pips": 6.585121154785156,
                    "previousSession": "LONDON",
                    "timestamp": "2025-11-05T07:58:00-06:00",
                    "time": "07:58:00"
                },
                {
                    "pair": "USDJPY",
                    "type": "HIGH",
                    "pips": 4670.10498046875,
                    "previousSession": "LONDON",
                    "timestamp": "2025-11-05T07:15:00-06:00",
                    "time": "07:15:00"
                },
                {
                    "pair": "USDCHF",
                    "type": "HIGH",
                    "pips": 7.700324058532715,
                    "previousSession": "LONDON",
                    "timestamp": "2025-11-05T09:00:00-06:00",
                    "time": "09:00:00"
                },
                {
                    "pair": "EURNZD",
                    "type": "LOW",
                    "pips": 2.9993057250976562,
                    "previousSession": "LONDON",
                    "timestamp": "2025-11-05T09:28:00-06:00",
                    "time": "09:28:00"
                },
                {
                    "pair": "EURCHF",
                    "type": "HIGH",
                    "pips": 1.500248908996582,
                    "previousSession": "LONDON",
                    "timestamp": "2025-11-05T09:01:00-06:00",
                    "time": "09:01:00"
                },
                {
                    "pair": "EURAUD",
                    "type": "LOW",
                    "pips": 26.89957618713379,
                    "previousSession": "LONDON",
                    "timestamp": "2025-11-05T07:55:00-06:00",
                    "time": "07:55:00"
                },
                {
                    "pair": "EURGBP",
                    "type": "LOW",
                    "pips": 1.6999244689941406,
                    "previousSession": "LONDON",
                    "timestamp": "2025-11-05T09:23:00-06:00",
                    "time": "09:23:00"
                },
                {
                    "pair": "GBPCHF",
                    "type": "HIGH",
                    "pips": 1.100301742553711,
                    "previousSession": "LONDON",
                    "timestamp": "2025-11-05T09:04:00-06:00",
                    "time": "09:04:00"
                },
                {
                    "pair": "GBPAUD",
                    "type": "LOW",
                    "pips": 22.59969711303711,
                    "previousSession": "LONDON",
                    "timestamp": "2025-11-05T08:40:00-06:00",
                    "time": "08:40:00"
                },
                {
                    "pair": "NZDCHF",
                    "type": "HIGH",
                    "pips": 0.7000565528869629,
                    "previousSession": "LONDON",
                    "timestamp": "2025-11-05T09:06:00-06:00",
                    "time": "09:06:00"
                },
                {
                    "pair": "NZDCHF",
                    "type": "LOW",
                    "pips": 12.800097465515137,
                    "previousSession": "LONDON",
                    "timestamp": "2025-11-05T07:14:00-06:00",
                    "time": "07:14:00"
                },
                {
                    "pair": "AUDNZD",
                    "type": "HIGH",
                    "pips": 15.900135040283203,
                    "previousSession": "LONDON",
                    "timestamp": "2025-11-05T07:21:00-06:00",
                    "time": "07:21:00"
                },
                {
                    "pair": "AUDNZD",
                    "type": "LOW",
                    "pips": 13.499259948730469,
                    "previousSession": "LONDON",
                    "timestamp": "2025-11-05T07:15:00-06:00",
                    "time": "07:15:00"
                },
                {
                    "pair": "AUDCHF",
                    "type": "HIGH",
                    "pips": 11.699795722961426,
                    "previousSession": "LONDON",
                    "timestamp": "2025-11-05T07:40:00-06:00",
                    "time": "07:40:00"
                },
                {
                    "pair": "AUDUSD",
                    "type": "HIGH",
                    "pips": 3.3801794052124023,
                    "previousSession": "LONDON",
                    "timestamp": "2025-11-05T08:53:00-06:00",
                    "time": "08:53:00"
                },
                {
                    "pair": "CADJPY",
                    "type": "HIGH",
                    "pips": 2890.0146484375,
                    "previousSession": "LONDON",
                    "timestamp": "2025-11-05T07:38:00-06:00",
                    "time": "07:38:00"
                },
                {
                    "pair": "EURJPY",
                    "type": "HIGH",
                    "pips": 4729.91943359375,
                    "previousSession": "LONDON",
                    "timestamp": "2025-11-05T07:03:00-06:00",
                    "time": "07:03:00"
                },
                {
                    "pair": "GBPJPY",
                    "type": "HIGH",
                    "pips": 6180.11474609375,
                    "previousSession": "LONDON",
                    "timestamp": "2025-11-05T07:15:00-06:00",
                    "time": "07:15:00"
                },
                {
                    "pair": "CHFJPY",
                    "type": "HIGH",
                    "pips": 5189.971923828125,
                    "previousSession": "LONDON",
                    "timestamp": "2025-11-05T07:03:00-06:00",
                    "time": "07:03:00"
                },
                {
                    "pair": "AUDJPY",
                    "type": "HIGH",
                    "pips": 4260.0250244140625,
                    "previousSession": "LONDON",
                    "timestamp": "2025-11-05T07:38:00-06:00",
                    "time": "07:38:00"
                }
            ]
        }
    },
    "currentSession": "NY",
    "correlations": {
        "USD": 0.2807422935883385,
        "EUR": 0.18096319567564473,
        "GBP": 0.3058373550823718,
        "CAD": 0.11312981343366071,
        "CHF": 0.23295731138609713,
        "AUD": 0.39403813208828337,
        "NZD": 0.31256006641606826,
        "JPY": 0.7218716373878674
    }
}