{
    "sessions": {
        "NY": {
            "name": "NY",
            "timeRange": "7:00 AM - 5:00 PM CT",
            "breaches": [
                {
                    "pair": "USDCAD",
                    "type": "HIGH",
                    "pips": 9.399652481079102,
                    "previousSession": "LONDON",
                    "timestamp": "2025-09-01T10:05:00-05:00",
                    "time": "10:05:00"
                },
                {
                    "pair": "EURCAD",
                    "type": "LOW",
                    "pips": 4.700422286987305,
                    "previousSession": "LONDON",
                    "timestamp": "2025-09-01T08:44:00-05:00",
                    "time": "08:44:00"
                },
                {
                    "pair": "GBPCAD",
                    "type": "HIGH",
                    "pips": 30.80010414123535,
                    "previousSession": "LONDON",
                    "timestamp": "2025-09-01T07:57:00-05:00",
                    "time": "07:57:00"
                },
                {
                    "pair": "CADCHF",
                    "type": "HIGH",
                    "pips": 2.200007438659668,
                    "previousSession": "LONDON",
                    "timestamp": "2025-09-01T07:00:00-05:00",
                    "time": "07:00:00"
                },
                {
                    "pair": "AUDCAD",
                    "type": "HIGH",
                    "pips": 7.599592208862305,
                    "previousSession": "LONDON",
                    "timestamp": "2025-09-01T09:24:00-05:00",
                    "time": "09:24:00"
                },
                {
                    "pair": "EURUSD",
                    "type": "LOW",
                    "pips": 16.454458236694336,
                    "previousSession": "LONDON",
                    "timestamp": "2025-09-01T07:14:00-05:00",
                    "time": "07:14:00"
                },
                {
                    "pair": "USDJPY",
                    "type": "HIGH",
                    "pips": 1029.96826171875,
                    "previousSession": "LONDON",
                    "timestamp": "2025-09-01T07:36:00-05:00",
                    "time": "07:36:00"
                },
                {
                    "pair": "GBPUSD",
                    "type": "HIGH",
                    "pips": 12.655258178710938,
                    "previousSession": "LONDON",
                    "timestamp": "2025-09-01T08:09:00-05:00",
                    "time": "08:09:00"
                },
                {
                    "pair": "USDCHF",
                    "type": "HIGH",
                    "pips": 11.799931526184082,
                    "previousSession": "LONDON",
                    "timestamp": "2025-09-01T07:00:00-05:00",
                    "time": "07:00:00"
                },
                {
                    "pair": "EURCHF",
                    "type": "HIGH",
                    "pips": 5.300045013427734,
                    "previousSession": "LONDON",
                    "timestamp": "2025-09-01T07:00:00-05:00",
                    "time": "07:00:00"
                },
                {
                    "pair": "EURAUD",
                    "type": "LOW",
                    "pips": 14.59956169128418,
                    "previousSession": "LONDON",
                    "timestamp": "2025-09-01T08:46:00-05:00",
                    "time": "08:46:00"
                },
                {
                    "pair": "EURGBP",
                    "type": "LOW",
                    "pips": 22.799968719482422,
                    "previousSession": "LONDON",
                    "timestamp": "2025-09-01T07:13:00-05:00",
                    "time": "07:13:00"
                },
                {
                    "pair": "GBPNZD",
                    "type": "HIGH",
                    "pips": 6.3991546630859375,
                    "previousSession": "LONDON",
                    "timestamp": "2025-09-01T11:08:00-05:00",
                    "time": "11:08:00"
                },
                {
                    "pair": "GBPCHF",
                    "type": "HIGH",
                    "pips": 32.999515533447266,
                    "previousSession": "LONDON",
                    "timestamp": "2025-09-01T07:00:00-05:00",
                    "time": "07:00:00"
                },
                {
                    "pair": "NZDCHF",
                    "type": "HIGH",
                    "pips": 2.7999281883239746,
                    "previousSession": "LONDON",
                    "timestamp": "2025-09-01T07:35:00-05:00",
                    "time": "07:35:00"
                },
                {
                    "pair": "AUDNZD",
                    "type": "HIGH",
                    "pips": 10.199546813964844,
                    "previousSession": "LONDON",
                    "timestamp": "2025-09-01T07:03:00-05:00",
                    "time": "07:03:00"
                },
                {
                    "pair": "AUDCHF",
                    "type": "HIGH",
                    "pips": 6.70015811920166,
                    "previousSession": "LONDON",
                    "timestamp": "2025-09-01T07:01:00-05:00",
                    "time": "07:01:00"
                },
                {
                    "pair": "CADJPY",
                    "type": "HIGH",
                    "pips": 249.93896484375,
                    "previousSession": "LONDON",
                    "timestamp": "2025-09-01T08:47:00-05:00",
                    "time": "08:47:00"
                },
                {
                    "pair": "EURJPY",
                    "type": "LOW",
                    "pips": 170.135498046875,
                    "previousSession": "LONDON",
                    "timestamp": "2025-09-01T11:00:00-05:00",
                    "time": "11:00:00"
                },
                {
                    "pair": "GBPJPY",
                    "type": "HIGH",
                    "pips": 4449.920654296875,
                    "previousSession": "LONDON",
                    "timestamp": "2025-09-01T07:33:00-05:00",
                    "time": "07:33:00"
                },
                {
                    "pair": "CHFJPY",
                    "type": "LOW",
                    "pips": 1220.0927734375,
                    "previousSession": "LONDON",
                    "timestamp": "2025-09-01T07:01:00-05:00",
                    "time": "07:01:00"
                },
                {
                    "pair": "AUDJPY",
                    "type": "HIGH",
                    "pips": 800.018310546875,
                    "previousSession": "LONDON",
                    "timestamp": "2025-09-01T09:02:00-05:00",
                    "time": "09:02:00"
                }
            ]
        }
    },
    "currentSession": "NY",
    "correlations": {
        "USD": 0.3340255129414822,
        "EUR": 0.2468272200786147,
        "GBP": 0.263771305185074,
        "CAD": 0.147773316692764,
        "CHF": 0.23098574642923586,
        "AUD": 0.22255642507779688,
        "NZD": 0.3174544083274036,
        "JPY": 0.6059526723114269
    }
}