{
    "sessions": {
        "NY": {
            "name": "NY",
            "timeRange": "7:00 AM - 5:00 PM CT",
            "breaches": [
                {
                    "pair": "USDCAD",
                    "type": "HIGH",
                    "pips": 30.59983253479004,
                    "previousSession": "LONDON",
                    "timestamp": "2026-03-03T08:41:00-06:00",
                    "time": "08:41:00"
                },
                {
                    "pair": "USDCAD",
                    "type": "LOW",
                    "pips": 24.00040626525879,
                    "previousSession": "LONDON",
                    "timestamp": "2026-03-03T10:14:00-06:00",
                    "time": "10:14:00"
                },
                {
                    "pair": "EURCAD",
                    "type": "LOW",
                    "pips": 41.800737380981445,
                    "previousSession": "LONDON",
                    "timestamp": "2026-03-03T08:15:00-06:00",
                    "time": "08:15:00"
                },
                {
                    "pair": "GBPCAD",
                    "type": "HIGH",
                    "pips": 21.200180053710938,
                    "previousSession": "LONDON",
                    "timestamp": "2026-03-03T08:34:00-06:00",
                    "time": "08:34:00"
                },
                {
                    "pair": "CADCHF",
                    "type": "LOW",
                    "pips": 10.499954223632812,
                    "previousSession": "LONDON",
                    "timestamp": "2026-03-03T08:41:00-06:00",
                    "time": "08:41:00"
                },
                {
                    "pair": "AUDCAD",
                    "type": "LOW",
                    "pips": 69.29993629455566,
                    "previousSession": "LONDON",
                    "timestamp": "2026-03-03T07:05:00-06:00",
                    "time": "07:05:00"
                },
                {
                    "pair": "NZDCAD",
                    "type": "LOW",
                    "pips": 13.599991798400879,
                    "previousSession": "LONDON",
                    "timestamp": "2026-03-03T09:08:00-06:00",
                    "time": "09:08:00"
                },
                {
                    "pair": "EURUSD",
                    "type": "LOW",
                    "pips": 50.786733627319336,
                    "previousSession": "LONDON",
                    "timestamp": "2026-03-03T08:21:00-06:00",
                    "time": "08:21:00"
                },
                {
                    "pair": "GBPUSD",
                    "type": "HIGH",
                    "pips": 35.300254821777344,
                    "previousSession": "LONDON",
                    "timestamp": "2026-03-03T11:49:00-06:00",
                    "time": "11:49:00"
                },
                {
                    "pair": "GBPUSD",
                    "type": "LOW",
                    "pips": 10.548830032348633,
                    "previousSession": "LONDON",
                    "timestamp": "2026-03-03T09:18:00-06:00",
                    "time": "09:18:00"
                },
                {
                    "pair": "USDCHF",
                    "type": "LOW",
                    "pips": 18.29981803894043,
                    "previousSession": "LONDON",
                    "timestamp": "2026-03-03T10:24:00-06:00",
                    "time": "10:24:00"
                },
                {
                    "pair": "NZDUSD",
                    "type": "LOW",
                    "pips": 26.7183780670166,
                    "previousSession": "LONDON",
                    "timestamp": "2026-03-03T08:57:00-06:00",
                    "time": "08:57:00"
                },
                {
                    "pair": "EURNZD",
                    "type": "HIGH",
                    "pips": 10.600090026855469,
                    "previousSession": "LONDON",
                    "timestamp": "2026-03-03T09:09:00-06:00",
                    "time": "09:09:00"
                },
                {
                    "pair": "EURCHF",
                    "type": "LOW",
                    "pips": 37.90020942687988,
                    "previousSession": "LONDON",
                    "timestamp": "2026-03-03T07:19:00-06:00",
                    "time": "07:19:00"
                },
                {
                    "pair": "EURAUD",
                    "type": "HIGH",
                    "pips": 94.59972381591797,
                    "previousSession": "LONDON",
                    "timestamp": "2026-03-03T07:09:00-06:00",
                    "time": "07:09:00"
                },
                {
                    "pair": "EURGBP",
                    "type": "LOW",
                    "pips": 18.6002254486084,
                    "previousSession": "LONDON",
                    "timestamp": "2026-03-03T08:13:00-06:00",
                    "time": "08:13:00"
                },
                {
                    "pair": "GBPNZD",
                    "type": "HIGH",
                    "pips": 53.40099334716797,
                    "previousSession": "LONDON",
                    "timestamp": "2026-03-03T08:53:00-06:00",
                    "time": "08:53:00"
                },
                {
                    "pair": "GBPCHF",
                    "type": "LOW",
                    "pips": 11.600255966186523,
                    "previousSession": "LONDON",
                    "timestamp": "2026-03-03T08:59:00-06:00",
                    "time": "08:59:00"
                },
                {
                    "pair": "GBPAUD",
                    "type": "HIGH",
                    "pips": 145.29943466186523,
                    "previousSession": "LONDON",
                    "timestamp": "2026-03-03T07:07:00-06:00",
                    "time": "07:07:00"
                },
                {
                    "pair": "NZDCHF",
                    "type": "LOW",
                    "pips": 26.29995346069336,
                    "previousSession": "LONDON",
                    "timestamp": "2026-03-03T08:35:00-06:00",
                    "time": "08:35:00"
                },
                {
                    "pair": "AUDNZD",
                    "type": "LOW",
                    "pips": 22.999048233032227,
                    "previousSession": "LONDON",
                    "timestamp": "2026-03-03T07:08:00-06:00",
                    "time": "07:08:00"
                },
                {
                    "pair": "AUDCHF",
                    "type": "LOW",
                    "pips": 53.59947681427002,
                    "previousSession": "LONDON",
                    "timestamp": "2026-03-03T07:08:00-06:00",
                    "time": "07:08:00"
                },
                {
                    "pair": "AUDUSD",
                    "type": "LOW",
                    "pips": 64.80097770690918,
                    "previousSession": "LONDON",
                    "timestamp": "2026-03-03T07:33:00-06:00",
                    "time": "07:33:00"
                },
                {
                    "pair": "CADJPY",
                    "type": "HIGH",
                    "pips": 2649.993896484375,
                    "previousSession": "LONDON",
                    "timestamp": "2026-03-03T07:11:00-06:00",
                    "time": "07:11:00"
                },
                {
                    "pair": "CADJPY",
                    "type": "LOW",
                    "pips": 2519.989013671875,
                    "previousSession": "LONDON",
                    "timestamp": "2026-03-03T08:48:00-06:00",
                    "time": "08:48:00"
                },
                {
                    "pair": "EURJPY",
                    "type": "LOW",
                    "pips": 7700.042724609375,
                    "previousSession": "LONDON",
                    "timestamp": "2026-03-03T08:24:00-06:00",
                    "time": "08:24:00"
                },
                {
                    "pair": "GBPJPY",
                    "type": "HIGH",
                    "pips": 5139.923095703125,
                    "previousSession": "LONDON",
                    "timestamp": "2026-03-03T08:19:00-06:00",
                    "time": "08:19:00"
                },
                {
                    "pair": "GBPJPY",
                    "type": "LOW",
                    "pips": 2030.029296875,
                    "previousSession": "LONDON",
                    "timestamp": "2026-03-03T09:01:00-06:00",
                    "time": "09:01:00"
                },
                {
                    "pair": "CHFJPY",
                    "type": "HIGH",
                    "pips": 6370.086669921875,
                    "previousSession": "LONDON",
                    "timestamp": "2026-03-03T10:00:00-06:00",
                    "time": "10:00:00"
                },
                {
                    "pair": "AUDJPY",
                    "type": "LOW",
                    "pips": 11360.015869140625,
                    "previousSession": "LONDON",
                    "timestamp": "2026-03-03T07:23:00-06:00",
                    "time": "07:23:00"
                }
            ]
        }
    },
    "currentSession": "NY",
    "correlations": {
        "USD": 0.31971926166177994,
        "EUR": 0.14457336986186017,
        "GBP": 0.26557002236430116,
        "CAD": 0.18377255527885855,
        "CHF": 0.42479467365186463,
        "AUD": 0.5756151523708825,
        "NZD": 0.27348038350891957,
        "JPY": 0.5124410711964206
    }
}