{
    "scoreMatrix": [
        {
            "currency": "EUR",
            "scores": [
                0
            ],
            "avg": 0.0
        },
        {
            "currency": "USD",
            "scores": [
                2,
                2,
                -2,
                2,
                0
            ],
            "avg": 0.8
        },
        {
            "currency": "AUD",
            "scores": [
                3,
                3,
                -3
            ],
            "avg": 1.0
        },
        {
            "currency": "CAD",
            "scores": [
                0
            ],
            "avg": 0.0
        }
    ]
}