{
    "scoreMatrix": [
        {
            "currency": "NZD",
            "scores": [
                0
            ],
            "avg": 0.0
        },
        {
            "currency": "GBP",
            "scores": [
                -2,
                -3,
                2,
                -3
            ],
            "avg": -1.5
        },
        {
            "currency": "AUD",
            "scores": [
                2,
                3
            ],
            "avg": 2.5
        }
    ]
}